mdpdf/__init__.py
mdpdf/cli.py
mdpdf/converter.py
mdpdf/font.py
mdpdf/headfoot.py
mdpdf/image.py
mdpdf/log.py
mdpdf/pdf_renderer.py
mdpdf/properties.py
mdpdf/style.py
mdpdf-0.0.18.dist-info/LICENSE
mdpdf-0.0.18.dist-info/METADATA
mdpdf-0.0.18.dist-info/WHEEL
mdpdf-0.0.18.dist-info/entry_points.txt
mdpdf-0.0.18.dist-info/top_level.txt
mdpdf-0.0.18.dist-info/RECORD
