Metadata-Version: 2.1
Name: mdpdf
Version: 0.0.18
Summary: Python command line application to convert Markdown to PDF.
Home-page: https://github.com/normanlorrain/mdpdf
Author: Norman Lorrain
Author-email: normanlorrain@gmail.com
License: MIT
Classifier: Development Status :: 3 - Alpha
Classifier: Intended Audience :: Developers
Classifier: Topic :: Software Development :: Libraries
Classifier: License :: OSI Approved :: MIT License
Classifier: Programming Language :: Python :: 3
Classifier: Operating System :: OS Independent
Requires-Python: >=3.8
License-File: LICENSE
Requires-Dist: pymupdf (>=1.21)
Requires-Dist: commonmark (>=0.9)
Requires-Dist: click (>=7.1)
